{
    "asset": {
        "format": "png",
        "id": "31bf6f665c775cb66db38c1606c429a8",
        "name": "ffxiv_20220626_082630_556.png",
        "path": "file:D:/workspace/github/gelehrte-languageecho/image/input/ffxiv_20220626_082630_556.png",
        "size": {
            "width": 418,
            "height": 128
        },
        "state": 2,
        "type": 1
    },
    "regions": [
        {
            "id": "cvcZx4t7p",
            "type": "RECTANGLE",
            "tags": [
                "s"
            ],
            "boundingBox": {
                "height": 45.053613053613056,
                "width": 39.35520684736091,
                "left": 350.0228245363766,
                "top": 11.836829836829837
            },
            "points": [
                {
                    "x": 350.0228245363766,
                    "y": 11.836829836829837
                },
                {
                    "x": 389.3780313837375,
                    "y": 11.836829836829837
                },
                {
                    "x": 389.3780313837375,
                    "y": 56.89044289044289
                },
                {
                    "x": 350.0228245363766,
                    "y": 56.89044289044289
                }
            ]
        },
        {
            "id": "_UUP21iT8",
            "type": "RECTANGLE",
            "tags": [
                "k"
            ],
            "boundingBox": {
                "height": 59.97202797202797,
                "width": 33.392296718972894,
                "left": 324.08416547788875,
                "top": 13.030303030303031
            },
            "points": [
                {
                    "x": 324.08416547788875,
                    "y": 13.030303030303031
                },
                {
                    "x": 357.47646219686163,
                    "y": 13.030303030303031
                },
                {
                    "x": 357.47646219686163,
                    "y": 73.002331002331
                },
                {
                    "x": 324.08416547788875,
                    "y": 73.002331002331
                }
            ]
        },
        {
            "id": "F2kRflutL",
            "type": "RECTANGLE",
            "tags": [
                "c"
            ],
            "boundingBox": {
                "height": 62.35897435897436,
                "width": 33.690442225392296,
                "left": 293.37517831669044,
                "top": 15.715617715617716
            },
            "points": [
                {
                    "x": 293.37517831669044,
                    "y": 15.715617715617716
                },
                {
                    "x": 327.06562054208274,
                    "y": 15.715617715617716
                },
                {
                    "x": 327.06562054208274,
                    "y": 78.07459207459208
                },
                {
                    "x": 293.37517831669044,
                    "y": 78.07459207459208
                }
            ]
        },
        {
            "id": "c8j_ZDEB6",
            "type": "RECTANGLE",
            "tags": [
                "e"
            ],
            "boundingBox": {
                "height": 44.75524475524475,
                "width": 35.4793152639087,
                "left": 262.06990014265335,
                "top": 16.312354312354312
            },
            "points": [
                {
                    "x": 262.06990014265335,
                    "y": 16.312354312354312
                },
                {
                    "x": 297.54921540656204,
                    "y": 16.312354312354312
                },
                {
                    "x": 297.54921540656204,
                    "y": 61.06759906759907
                },
                {
                    "x": 262.06990014265335,
                    "y": 61.06759906759907
                }
            ]
        },
        {
            "id": "D2tbc6F67",
            "type": "RECTANGLE",
            "tags": [
                "D"
            ],
            "boundingBox": {
                "height": 57.883449883449885,
                "width": 43.23109843081313,
                "left": 220.62767475035662,
                "top": 6.1678321678321675
            },
            "points": [
                {
                    "x": 220.62767475035662,
                    "y": 6.1678321678321675
                },
                {
                    "x": 263.85877318116974,
                    "y": 6.1678321678321675
                },
                {
                    "x": 263.85877318116974,
                    "y": 64.05128205128206
                },
                {
                    "x": 220.62767475035662,
                    "y": 64.05128205128206
                }
            ]
        },
        {
            "id": "g3knsFZAo",
            "type": "RECTANGLE",
            "tags": [
                "r"
            ],
            "boundingBox": {
                "height": 59.07692307692308,
                "width": 45.019971469329526,
                "left": 167.55777460770327,
                "top": 24.06993006993007
            },
            "points": [
                {
                    "x": 167.55777460770327,
                    "y": 24.06993006993007
                },
                {
                    "x": 212.5777460770328,
                    "y": 24.06993006993007
                },
                {
                    "x": 212.5777460770328,
                    "y": 83.14685314685315
                },
                {
                    "x": 167.55777460770327,
                    "y": 83.14685314685315
                }
            ]
        },
        {
            "id": "IMwO6XBJt",
            "type": "RECTANGLE",
            "tags": [
                "e"
            ],
            "boundingBox": {
                "height": 48.93240093240093,
                "width": 33.9885877318117,
                "left": 137.1469329529244,
                "top": 24.06993006993007
            },
            "points": [
                {
                    "x": 137.1469329529244,
                    "y": 24.06993006993007
                },
                {
                    "x": 171.1355206847361,
                    "y": 24.06993006993007
                },
                {
                    "x": 171.1355206847361,
                    "y": 73.002331002331
                },
                {
                    "x": 137.1469329529244,
                    "y": 73.002331002331
                }
            ]
        },
        {
            "id": "CPeaqC2aE",
            "type": "RECTANGLE",
            "tags": [
                "w"
            ],
            "boundingBox": {
                "height": 46.84382284382284,
                "width": 50.68473609129814,
                "left": 89.74179743223965,
                "top": 26.456876456876458
            },
            "points": [
                {
                    "x": 89.74179743223965,
                    "y": 26.456876456876458
                },
                {
                    "x": 140.4265335235378,
                    "y": 26.456876456876458
                },
                {
                    "x": 140.4265335235378,
                    "y": 73.3006993006993
                },
                {
                    "x": 89.74179743223965,
                    "y": 73.3006993006993
                }
            ]
        },
        {
            "id": "AViQvyk4p",
            "type": "RECTANGLE",
            "tags": [
                "o"
            ],
            "boundingBox": {
                "height": 44.158508158508155,
                "width": 35.777460770328105,
                "left": 61.417974322396574,
                "top": 27.35198135198135
            },
            "points": [
                {
                    "x": 61.417974322396574,
                    "y": 27.35198135198135
                },
                {
                    "x": 97.19543509272468,
                    "y": 27.35198135198135
                },
                {
                    "x": 97.19543509272468,
                    "y": 71.5104895104895
                },
                {
                    "x": 61.417974322396574,
                    "y": 71.5104895104895
                }
            ]
        },
        {
            "id": "25aSWPo1d",
            "type": "RECTANGLE",
            "tags": [
                "L"
            ],
            "boundingBox": {
                "height": 56.98834498834499,
                "width": 39.951497860199716,
                "left": 23.255349500713265,
                "top": 17.20745920745921
            },
            "points": [
                {
                    "x": 23.255349500713265,
                    "y": 17.20745920745921
                },
                {
                    "x": 63.20684736091298,
                    "y": 17.20745920745921
                },
                {
                    "x": 63.20684736091298,
                    "y": 74.1958041958042
                },
                {
                    "x": 23.255349500713265,
                    "y": 74.1958041958042
                }
            ]
        }
    ],
    "version": "2.2.0"
}