{
    "asset": {
        "format": "png",
        "id": "6cc29291837e4e8d725efb231f30e964",
        "name": "ffxiv_20221029_075356_588.png",
        "path": "file:D:/workspace/github/gelehrte-languageecho/image-FF14-letters/input/ffxiv_20221029_075356_588.png",
        "size": {
            "width": 1920,
            "height": 1080
        },
        "state": 2,
        "type": 1
    },
    "regions": [
        {
            "id": "Mlmr0qwEU",
            "type": "RECTANGLE",
            "tags": [
                "letters"
            ],
            "boundingBox": {
                "height": 151.78378378378378,
                "width": 1305.3079847908746,
                "left": 119.72623574144487,
                "top": 163.2314189189189
            },
            "points": [
                {
                    "x": 119.72623574144487,
                    "y": 163.2314189189189
                },
                {
                    "x": 1425.0342205323195,
                    "y": 163.2314189189189
                },
                {
                    "x": 1425.0342205323195,
                    "y": 315.0152027027027
                },
                {
                    "x": 119.72623574144487,
                    "y": 315.0152027027027
                }
            ]
        },
        {
            "id": "OqYrDIHA1",
            "type": "RECTANGLE",
            "tags": [
                "letters"
            ],
            "boundingBox": {
                "height": 87.56756756756756,
                "width": 220.47148288973384,
                "left": 242.37262357414448,
                "top": 307.7179054054054
            },
            "points": [
                {
                    "x": 242.37262357414448,
                    "y": 307.7179054054054
                },
                {
                    "x": 462.84410646387835,
                    "y": 307.7179054054054
                },
                {
                    "x": 462.84410646387835,
                    "y": 395.28547297297297
                },
                {
                    "x": 242.37262357414448,
                    "y": 395.28547297297297
                }
            ]
        },
        {
            "id": "DXjHEZuH-",
            "type": "RECTANGLE",
            "tags": [
                "letters"
            ],
            "boundingBox": {
                "height": 110.91891891891892,
                "width": 204.4106463878327,
                "left": 1024.9733840304182,
                "top": 316.47466216216213
            },
            "points": [
                {
                    "x": 1024.9733840304182,
                    "y": 316.47466216216213
                },
                {
                    "x": 1229.384030418251,
                    "y": 316.47466216216213
                },
                {
                    "x": 1229.384030418251,
                    "y": 427.3935810810811
                },
                {
                    "x": 1024.9733840304182,
                    "y": 427.3935810810811
                }
            ]
        },
        {
            "id": "votoEEabs",
            "type": "RECTANGLE",
            "tags": [
                "letters"
            ],
            "boundingBox": {
                "height": 80.27027027027027,
                "width": 214.63117870722434,
                "left": 127.02661596958175,
                "top": 411.33952702702703
            },
            "points": [
                {
                    "x": 127.02661596958175,
                    "y": 411.33952702702703
                },
                {
                    "x": 341.6577946768061,
                    "y": 411.33952702702703
                },
                {
                    "x": 341.6577946768061,
                    "y": 491.6097972972973
                },
                {
                    "x": 127.02661596958175,
                    "y": 491.6097972972973
                }
            ]
        },
        {
            "id": "C-FYUWkbK",
            "type": "RECTANGLE",
            "tags": [
                "letters"
            ],
            "boundingBox": {
                "height": 87.56756756756756,
                "width": 186.8897338403042,
                "left": 452.6235741444867,
                "top": 415.7179054054054
            },
            "points": [
                {
                    "x": 452.6235741444867,
                    "y": 415.7179054054054
                },
                {
                    "x": 639.5133079847909,
                    "y": 415.7179054054054
                },
                {
                    "x": 639.5133079847909,
                    "y": 503.28547297297297
                },
                {
                    "x": 452.6235741444867,
                    "y": 503.28547297297297
                }
            ]
        },
        {
            "id": "fHTzep1Ju",
            "type": "RECTANGLE",
            "tags": [
                "letters"
            ],
            "boundingBox": {
                "height": 59.83783783783784,
                "width": 220.47148288973384,
                "left": 797.2015209125476,
                "top": 452.2043918918919
            },
            "points": [
                {
                    "x": 797.2015209125476,
                    "y": 452.2043918918919
                },
                {
                    "x": 1017.6730038022814,
                    "y": 452.2043918918919
                },
                {
                    "x": 1017.6730038022814,
                    "y": 512.0422297297297
                },
                {
                    "x": 797.2015209125476,
                    "y": 512.0422297297297
                }
            ]
        },
        {
            "id": "h2NNtUvgo",
            "type": "RECTANGLE",
            "tags": [
                "letters"
            ],
            "boundingBox": {
                "height": 55.45945945945946,
                "width": 220.47148288973384,
                "left": 1035.19391634981,
                "top": 462.4206081081081
            },
            "points": [
                {
                    "x": 1035.19391634981,
                    "y": 462.4206081081081
                },
                {
                    "x": 1255.6653992395438,
                    "y": 462.4206081081081
                },
                {
                    "x": 1255.6653992395438,
                    "y": 517.8800675675676
                },
                {
                    "x": 1035.19391634981,
                    "y": 517.8800675675676
                }
            ]
        },
        {
            "id": "K__QUSMbH",
            "type": "RECTANGLE",
            "tags": [
                "letters"
            ],
            "boundingBox": {
                "height": 62.75675675675676,
                "width": 201.49049429657796,
                "left": 1264.425855513308,
                "top": 465.33952702702703
            },
            "points": [
                {
                    "x": 1264.425855513308,
                    "y": 465.33952702702703
                },
                {
                    "x": 1465.916349809886,
                    "y": 465.33952702702703
                },
                {
                    "x": 1465.916349809886,
                    "y": 528.0962837837837
                },
                {
                    "x": 1264.425855513308,
                    "y": 528.0962837837837
                }
            ]
        },
        {
            "id": "Zr7MnTPvD",
            "type": "RECTANGLE",
            "tags": [
                "letters"
            ],
            "boundingBox": {
                "height": 68.5945945945946,
                "width": 332.89733840304183,
                "left": 59.863117870722434,
                "top": 544.1503378378378
            },
            "points": [
                {
                    "x": 59.863117870722434,
                    "y": 544.1503378378378
                },
                {
                    "x": 392.76045627376425,
                    "y": 544.1503378378378
                },
                {
                    "x": 392.76045627376425,
                    "y": 612.7449324324324
                },
                {
                    "x": 59.863117870722434,
                    "y": 612.7449324324324
                }
            ]
        },
        {
            "id": "TQPMHrT_w",
            "type": "RECTANGLE",
            "tags": [
                "letters"
            ],
            "boundingBox": {
                "height": 83.1891891891892,
                "width": 331.43726235741445,
                "left": 400.0608365019012,
                "top": 533.9341216216216
            },
            "points": [
                {
                    "x": 400.0608365019012,
                    "y": 533.9341216216216
                },
                {
                    "x": 731.4980988593156,
                    "y": 533.9341216216216
                },
                {
                    "x": 731.4980988593156,
                    "y": 617.1233108108108
                },
                {
                    "x": 400.0608365019012,
                    "y": 617.1233108108108
                }
            ]
        },
        {
            "id": "gJRL3BE-h",
            "type": "RECTANGLE",
            "tags": [
                "letters"
            ],
            "boundingBox": {
                "height": 68.5945945945946,
                "width": 313.91634980988596,
                "left": 78.84410646387833,
                "top": 605.4476351351351
            },
            "points": [
                {
                    "x": 78.84410646387833,
                    "y": 605.4476351351351
                },
                {
                    "x": 392.76045627376425,
                    "y": 605.4476351351351
                },
                {
                    "x": 392.76045627376425,
                    "y": 674.0422297297297
                },
                {
                    "x": 78.84410646387833,
                    "y": 674.0422297297297
                }
            ]
        },
        {
            "id": "3QsBPhRt2",
            "type": "RECTANGLE",
            "tags": [
                "letters"
            ],
            "boundingBox": {
                "height": 61.2972972972973,
                "width": 350.4182509505704,
                "left": 384,
                "top": 598.1503378378378
            },
            "points": [
                {
                    "x": 384,
                    "y": 598.1503378378378
                },
                {
                    "x": 734.4182509505704,
                    "y": 598.1503378378378
                },
                {
                    "x": 734.4182509505704,
                    "y": 659.4476351351351
                },
                {
                    "x": 384,
                    "y": 659.4476351351351
                }
            ]
        },
        {
            "id": "Fiek2uUKO",
            "type": "RECTANGLE",
            "tags": [
                "letters"
            ],
            "boundingBox": {
                "height": 54,
                "width": 322.6768060836502,
                "left": 70.08365019011407,
                "top": 657.9881756756756
            },
            "points": [
                {
                    "x": 70.08365019011407,
                    "y": 657.9881756756756
                },
                {
                    "x": 392.76045627376425,
                    "y": 657.9881756756756
                },
                {
                    "x": 392.76045627376425,
                    "y": 711.9881756756756
                },
                {
                    "x": 70.08365019011407,
                    "y": 711.9881756756756
                }
            ]
        },
        {
            "id": "Eb3qlCKKk",
            "type": "RECTANGLE",
            "tags": [
                "letters"
            ],
            "boundingBox": {
                "height": 64.21621621621621,
                "width": 348.95817490494295,
                "left": 394.2205323193916,
                "top": 659.4476351351351
            },
            "points": [
                {
                    "x": 394.2205323193916,
                    "y": 659.4476351351351
                },
                {
                    "x": 743.1787072243346,
                    "y": 659.4476351351351
                },
                {
                    "x": 743.1787072243346,
                    "y": 723.6638513513514
                },
                {
                    "x": 394.2205323193916,
                    "y": 723.6638513513514
                }
            ]
        },
        {
            "id": "SEkqh9wM9",
            "type": "RECTANGLE",
            "tags": [
                "letters"
            ],
            "boundingBox": {
                "height": 80.27027027027027,
                "width": 354.7984790874525,
                "left": 397.1406844106464,
                "top": 707.6097972972973
            },
            "points": [
                {
                    "x": 397.1406844106464,
                    "y": 707.6097972972973
                },
                {
                    "x": 751.9391634980989,
                    "y": 707.6097972972973
                },
                {
                    "x": 751.9391634980989,
                    "y": 787.8800675675676
                },
                {
                    "x": 397.1406844106464,
                    "y": 787.8800675675676
                }
            ]
        },
        {
            "id": "huo7FWcnV",
            "type": "RECTANGLE",
            "tags": [
                "letters"
            ],
            "boundingBox": {
                "height": 61.2972972972973,
                "width": 224.851711026616,
                "left": 800.1216730038024,
                "top": 514.9611486486486
            },
            "points": [
                {
                    "x": 800.1216730038024,
                    "y": 514.9611486486486
                },
                {
                    "x": 1024.9733840304182,
                    "y": 514.9611486486486
                },
                {
                    "x": 1024.9733840304182,
                    "y": 576.2584459459459
                },
                {
                    "x": 800.1216730038024,
                    "y": 576.2584459459459
                }
            ]
        },
        {
            "id": "2PLVhCP7E",
            "type": "RECTANGLE",
            "tags": [
                "letters"
            ],
            "boundingBox": {
                "height": 72.97297297297297,
                "width": 219.01140684410646,
                "left": 1033.7338403041826,
                "top": 520.7989864864865
            },
            "points": [
                {
                    "x": 1033.7338403041826,
                    "y": 520.7989864864865
                },
                {
                    "x": 1252.745247148289,
                    "y": 520.7989864864865
                },
                {
                    "x": 1252.745247148289,
                    "y": 593.7719594594595
                },
                {
                    "x": 1033.7338403041826,
                    "y": 593.7719594594595
                }
            ]
        },
        {
            "id": "fbP727tKq",
            "type": "RECTANGLE",
            "tags": [
                "letters"
            ],
            "boundingBox": {
                "height": 59.83783783783784,
                "width": 188.34980988593156,
                "left": 1251.2851711026617,
                "top": 529.5557432432432
            },
            "points": [
                {
                    "x": 1251.2851711026617,
                    "y": 529.5557432432432
                },
                {
                    "x": 1439.6349809885933,
                    "y": 529.5557432432432
                },
                {
                    "x": 1439.6349809885933,
                    "y": 589.393581081081
                },
                {
                    "x": 1251.2851711026617,
                    "y": 589.393581081081
                }
            ]
        },
        {
            "id": "0sz43VaEc",
            "type": "RECTANGLE",
            "tags": [
                "letters"
            ],
            "boundingBox": {
                "height": 52.54054054054054,
                "width": 221.93155893536124,
                "left": 800.1216730038024,
                "top": 574.7989864864865
            },
            "points": [
                {
                    "x": 800.1216730038024,
                    "y": 574.7989864864865
                },
                {
                    "x": 1022.0532319391635,
                    "y": 574.7989864864865
                },
                {
                    "x": 1022.0532319391635,
                    "y": 627.339527027027
                },
                {
                    "x": 800.1216730038024,
                    "y": 627.339527027027
                }
            ]
        },
        {
            "id": "2acWw42GW",
            "type": "RECTANGLE",
            "tags": [
                "letters"
            ],
            "boundingBox": {
                "height": 51.08108108108108,
                "width": 227.77186311787074,
                "left": 1026.4334600760455,
                "top": 592.3125
            },
            "points": [
                {
                    "x": 1026.4334600760455,
                    "y": 592.3125
                },
                {
                    "x": 1254.2053231939165,
                    "y": 592.3125
                },
                {
                    "x": 1254.2053231939165,
                    "y": 643.393581081081
                },
                {
                    "x": 1026.4334600760455,
                    "y": 643.393581081081
                }
            ]
        },
        {
            "id": "JO_xTv8NO",
            "type": "RECTANGLE",
            "tags": [
                "letters"
            ],
            "boundingBox": {
                "height": 67.13513513513513,
                "width": 179.58935361216732,
                "left": 1260.045627376426,
                "top": 596.6908783783783
            },
            "points": [
                {
                    "x": 1260.045627376426,
                    "y": 596.6908783783783
                },
                {
                    "x": 1439.6349809885933,
                    "y": 596.6908783783783
                },
                {
                    "x": 1439.6349809885933,
                    "y": 663.8260135135135
                },
                {
                    "x": 1260.045627376426,
                    "y": 663.8260135135135
                }
            ]
        },
        {
            "id": "Ne_RHXRPe",
            "type": "RECTANGLE",
            "tags": [
                "letters"
            ],
            "boundingBox": {
                "height": 64.21621621621621,
                "width": 157.68821292775667,
                "left": 1264.425855513308,
                "top": 650.6908783783783
            },
            "points": [
                {
                    "x": 1264.425855513308,
                    "y": 650.6908783783783
                },
                {
                    "x": 1422.1140684410648,
                    "y": 650.6908783783783
                },
                {
                    "x": 1422.1140684410648,
                    "y": 714.9070945945946
                },
                {
                    "x": 1264.425855513308,
                    "y": 714.9070945945946
                }
            ]
        },
        {
            "id": "bTix9Yz8i",
            "type": "RECTANGLE",
            "tags": [
                "letters"
            ],
            "boundingBox": {
                "height": 65.67567567567568,
                "width": 232.15209125475286,
                "left": 1022.0532319391635,
                "top": 634.6368243243243
            },
            "points": [
                {
                    "x": 1022.0532319391635,
                    "y": 634.6368243243243
                },
                {
                    "x": 1254.2053231939165,
                    "y": 634.6368243243243
                },
                {
                    "x": 1254.2053231939165,
                    "y": 700.3125
                },
                {
                    "x": 1022.0532319391635,
                    "y": 700.3125
                }
            ]
        },
        {
            "id": "VsU9v2-CF",
            "type": "RECTANGLE",
            "tags": [
                "letters"
            ],
            "boundingBox": {
                "height": 55.45945945945946,
                "width": 224.851711026616,
                "left": 800.1216730038024,
                "top": 627.339527027027
            },
            "points": [
                {
                    "x": 800.1216730038024,
                    "y": 627.339527027027
                },
                {
                    "x": 1024.9733840304182,
                    "y": 627.339527027027
                },
                {
                    "x": 1024.9733840304182,
                    "y": 682.7989864864865
                },
                {
                    "x": 800.1216730038024,
                    "y": 682.7989864864865
                }
            ]
        },
        {
            "id": "GikmLDsP2",
            "type": "RECTANGLE",
            "tags": [
                "letters"
            ],
            "boundingBox": {
                "height": 61.2972972972973,
                "width": 227.77186311787074,
                "left": 795.7414448669202,
                "top": 682.7989864864865
            },
            "points": [
                {
                    "x": 795.7414448669202,
                    "y": 682.7989864864865
                },
                {
                    "x": 1023.5133079847909,
                    "y": 682.7989864864865
                },
                {
                    "x": 1023.5133079847909,
                    "y": 744.0962837837837
                },
                {
                    "x": 795.7414448669202,
                    "y": 744.0962837837837
                }
            ]
        },
        {
            "id": "5zj4meBOK",
            "type": "RECTANGLE",
            "tags": [
                "letters"
            ],
            "boundingBox": {
                "height": 65.67567567567568,
                "width": 227.77186311787074,
                "left": 1023.5133079847909,
                "top": 700.3125
            },
            "points": [
                {
                    "x": 1023.5133079847909,
                    "y": 700.3125
                },
                {
                    "x": 1251.2851711026617,
                    "y": 700.3125
                },
                {
                    "x": 1251.2851711026617,
                    "y": 765.9881756756756
                },
                {
                    "x": 1023.5133079847909,
                    "y": 765.9881756756756
                }
            ]
        },
        {
            "id": "FRivVaqza",
            "type": "RECTANGLE",
            "tags": [
                "letters"
            ],
            "boundingBox": {
                "height": 61.2972972972973,
                "width": 125.56653992395438,
                "left": 1249.8250950570343,
                "top": 717.8260135135135
            },
            "points": [
                {
                    "x": 1249.8250950570343,
                    "y": 717.8260135135135
                },
                {
                    "x": 1375.3916349809886,
                    "y": 717.8260135135135
                },
                {
                    "x": 1375.3916349809886,
                    "y": 779.1233108108108
                },
                {
                    "x": 1249.8250950570343,
                    "y": 779.1233108108108
                }
            ]
        },
        {
            "id": "1N-N6kg2b",
            "type": "RECTANGLE",
            "tags": [
                "letters"
            ],
            "boundingBox": {
                "height": 35.027027027027025,
                "width": 127.02661596958175,
                "left": 1554.9809885931559,
                "top": 101.93412162162161
            },
            "points": [
                {
                    "x": 1554.9809885931559,
                    "y": 101.93412162162161
                },
                {
                    "x": 1682.0076045627377,
                    "y": 101.93412162162161
                },
                {
                    "x": 1682.0076045627377,
                    "y": 136.96114864864865
                },
                {
                    "x": 1554.9809885931559,
                    "y": 136.96114864864865
                }
            ]
        },
        {
            "id": "SwyAD77hl",
            "type": "RECTANGLE",
            "tags": [
                "letters"
            ],
            "boundingBox": {
                "height": 20.43243243243243,
                "width": 129.94676806083652,
                "left": 1550.6007604562737,
                "top": 136.96114864864865
            },
            "points": [
                {
                    "x": 1550.6007604562737,
                    "y": 136.96114864864865
                },
                {
                    "x": 1680.5475285171103,
                    "y": 136.96114864864865
                },
                {
                    "x": 1680.5475285171103,
                    "y": 157.39358108108107
                },
                {
                    "x": 1550.6007604562737,
                    "y": 157.39358108108107
                }
            ]
        },
        {
            "id": "n9pBx_o3o",
            "type": "RECTANGLE",
            "tags": [
                "letters"
            ],
            "boundingBox": {
                "height": 27.72972972972973,
                "width": 105.1254752851711,
                "left": 1549.1406844106464,
                "top": 160.3125
            },
            "points": [
                {
                    "x": 1549.1406844106464,
                    "y": 160.3125
                },
                {
                    "x": 1654.2661596958176,
                    "y": 160.3125
                },
                {
                    "x": 1654.2661596958176,
                    "y": 188.0422297297297
                },
                {
                    "x": 1549.1406844106464,
                    "y": 188.0422297297297
                }
            ]
        },
        {
            "id": "sl6isevyL",
            "type": "RECTANGLE",
            "tags": [
                "letters"
            ],
            "boundingBox": {
                "height": 29.18918918918919,
                "width": 100.74524714828898,
                "left": 1549.1406844106464,
                "top": 186.58277027027026
            },
            "points": [
                {
                    "x": 1549.1406844106464,
                    "y": 186.58277027027026
                },
                {
                    "x": 1649.8859315589355,
                    "y": 186.58277027027026
                },
                {
                    "x": 1649.8859315589355,
                    "y": 215.77195945945945
                },
                {
                    "x": 1549.1406844106464,
                    "y": 215.77195945945945
                }
            ]
        },
        {
            "id": "YIxlyIB3q",
            "type": "RECTANGLE",
            "tags": [
                "letters"
            ],
            "boundingBox": {
                "height": 56.91891891891892,
                "width": 96.36501901140684,
                "left": 1449.855513307985,
                "top": 212.85304054054055
            },
            "points": [
                {
                    "x": 1449.855513307985,
                    "y": 212.85304054054055
                },
                {
                    "x": 1546.2205323193916,
                    "y": 212.85304054054055
                },
                {
                    "x": 1546.2205323193916,
                    "y": 269.7719594594595
                },
                {
                    "x": 1449.855513307985,
                    "y": 269.7719594594595
                }
            ]
        },
        {
            "id": "afJoTYWfW",
            "type": "RECTANGLE",
            "tags": [
                "letters"
            ],
            "boundingBox": {
                "height": 42.32432432432432,
                "width": 124.106463878327,
                "left": 1444.0152091254754,
                "top": 284.36655405405406
            },
            "points": [
                {
                    "x": 1444.0152091254754,
                    "y": 284.36655405405406
                },
                {
                    "x": 1568.1216730038022,
                    "y": 284.36655405405406
                },
                {
                    "x": 1568.1216730038022,
                    "y": 326.6908783783784
                },
                {
                    "x": 1444.0152091254754,
                    "y": 326.6908783783784
                }
            ]
        },
        {
            "id": "Xpr7YnePQ",
            "type": "RECTANGLE",
            "tags": [
                "letters"
            ],
            "boundingBox": {
                "height": 30.64864864864865,
                "width": 124.106463878327,
                "left": 1448.3954372623575,
                "top": 332.5287162162162
            },
            "points": [
                {
                    "x": 1448.3954372623575,
                    "y": 332.5287162162162
                },
                {
                    "x": 1572.5019011406844,
                    "y": 332.5287162162162
                },
                {
                    "x": 1572.5019011406844,
                    "y": 363.17736486486484
                },
                {
                    "x": 1448.3954372623575,
                    "y": 363.17736486486484
                }
            ]
        },
        {
            "id": "FIY2fICn3",
            "type": "RECTANGLE",
            "tags": [
                "letters"
            ],
            "boundingBox": {
                "height": 33.567567567567565,
                "width": 179.58935361216732,
                "left": 1442.555133079848,
                "top": 580.6368243243243
            },
            "points": [
                {
                    "x": 1442.555133079848,
                    "y": 580.6368243243243
                },
                {
                    "x": 1622.1444866920153,
                    "y": 580.6368243243243
                },
                {
                    "x": 1622.1444866920153,
                    "y": 614.2043918918919
                },
                {
                    "x": 1442.555133079848,
                    "y": 614.2043918918919
                }
            ]
        },
        {
            "id": "262uJoaKU",
            "type": "RECTANGLE",
            "tags": [
                "letters"
            ],
            "boundingBox": {
                "height": 26.27027027027027,
                "width": 105.1254752851711,
                "left": 1476.1368821292776,
                "top": 474.09628378378375
            },
            "points": [
                {
                    "x": 1476.1368821292776,
                    "y": 474.09628378378375
                },
                {
                    "x": 1581.2623574144486,
                    "y": 474.09628378378375
                },
                {
                    "x": 1581.2623574144486,
                    "y": 500.36655405405406
                },
                {
                    "x": 1476.1368821292776,
                    "y": 500.36655405405406
                }
            ]
        }
    ],
    "version": "2.2.0"
}