{
    "asset": {
        "format": "png",
        "id": "6fe5d5b8ab3f70c2f47dc58ca6b53262",
        "name": "ffxiv_20230807_083902_765.png",
        "path": "file:D:/workspace/github/gelehrte-languageecho/image-FF14-letters/input/ffxiv_20230807_083902_765.png",
        "size": {
            "width": 1920,
            "height": 1080
        },
        "state": 2,
        "type": 1
    },
    "regions": [
        {
            "id": "PIVys9xJp",
            "type": "RECTANGLE",
            "tags": [
                "letters"
            ],
            "boundingBox": {
                "height": 102.79357231149567,
                "width": 799.221681723419,
                "left": 337.56775538568445,
                "top": 785.9286155747836
            },
            "points": [
                {
                    "x": 337.56775538568445,
                    "y": 785.9286155747836
                },
                {
                    "x": 1136.7894371091033,
                    "y": 785.9286155747836
                },
                {
                    "x": 1136.7894371091033,
                    "y": 888.7221878862794
                },
                {
                    "x": 337.56775538568445,
                    "y": 888.7221878862794
                }
            ]
        },
        {
            "id": "52ZNMjgw8",
            "type": "RECTANGLE",
            "tags": [
                "letters"
            ],
            "boundingBox": {
                "height": 125.48825710754016,
                "width": 796.5531619179985,
                "left": 336.23349548297426,
                "top": 689.8099505562423
            },
            "points": [
                {
                    "x": 336.23349548297426,
                    "y": 689.8099505562423
                },
                {
                    "x": 1132.786657400973,
                    "y": 689.8099505562423
                },
                {
                    "x": 1132.786657400973,
                    "y": 815.2982076637824
                },
                {
                    "x": 336.23349548297426,
                    "y": 815.2982076637824
                }
            ]
        },
        {
            "id": "LvQaJtCSI",
            "type": "RECTANGLE",
            "tags": [
                "letters"
            ],
            "boundingBox": {
                "height": 114.80840543881334,
                "width": 832.5781792911744,
                "left": 326.8936761640027,
                "top": 564.321693448702
            },
            "points": [
                {
                    "x": 326.8936761640027,
                    "y": 564.321693448702
                },
                {
                    "x": 1159.471855455177,
                    "y": 564.321693448702
                },
                {
                    "x": 1159.471855455177,
                    "y": 679.1300988875154
                },
                {
                    "x": 326.8936761640027,
                    "y": 679.1300988875154
                }
            ]
        },
        {
            "id": "TGBGuusQC",
            "type": "RECTANGLE",
            "tags": [
                "letters"
            ],
            "boundingBox": {
                "height": 109.46847960444993,
                "width": 885.948575399583,
                "left": 301.54273801250866,
                "top": 482.88782447466
            },
            "points": [
                {
                    "x": 301.54273801250866,
                    "y": 482.88782447466
                },
                {
                    "x": 1187.4913134120916,
                    "y": 482.88782447466
                },
                {
                    "x": 1187.4913134120916,
                    "y": 592.3563040791099
                },
                {
                    "x": 301.54273801250866,
                    "y": 592.3563040791099
                }
            ]
        },
        {
            "id": "sNAUiT4Rf",
            "type": "RECTANGLE",
            "tags": [
                "letters"
            ],
            "boundingBox": {
                "height": 134.83312731767614,
                "width": 1018.0403057678943,
                "left": 244.1695621959694,
                "top": 326.6949938195303
            },
            "points": [
                {
                    "x": 244.1695621959694,
                    "y": 326.6949938195303
                },
                {
                    "x": 1262.2098679638636,
                    "y": 326.6949938195303
                },
                {
                    "x": 1262.2098679638636,
                    "y": 461.5281211372064
                },
                {
                    "x": 244.1695621959694,
                    "y": 461.5281211372064
                }
            ]
        },
        {
            "id": "Y4mW-Ubi3",
            "type": "RECTANGLE",
            "tags": [
                "letters"
            ],
            "boundingBox": {
                "height": 124.15327564894932,
                "width": 1011.3690062543433,
                "left": 241.50104239054897,
                "top": 234.5812731767614
            },
            "points": [
                {
                    "x": 241.50104239054897,
                    "y": 234.5812731767614
                },
                {
                    "x": 1252.8700486448922,
                    "y": 234.5812731767614
                },
                {
                    "x": 1252.8700486448922,
                    "y": 358.7345488257107
                },
                {
                    "x": 241.50104239054897,
                    "y": 358.7345488257107
                }
            ]
        }
    ],
    "version": "2.2.0"
}