{
    "asset": {
        "format": "png",
        "id": "b6f534adb69518e9a6a45c75b66267d7",
        "name": "ffxiv_20230720_220846_367.png",
        "path": "file:D:/workspace/github/gelehrte-languageecho/image-FF14-letters/input/ffxiv_20230720_220846_367.png",
        "size": {
            "width": 1920,
            "height": 1080
        },
        "state": 2,
        "type": 1
    },
    "regions": [
        {
            "id": "YmASEFU3o",
            "type": "RECTANGLE",
            "tags": [
                "letters_l_90"
            ],
            "boundingBox": {
                "height": 349.76514215080346,
                "width": 294.87143849895756,
                "left": 0,
                "top": 476.2129171817058
            },
            "points": [
                {
                    "x": 0,
                    "y": 476.2129171817058
                },
                {
                    "x": 294.87143849895756,
                    "y": 476.2129171817058
                },
                {
                    "x": 294.87143849895756,
                    "y": 825.9780593325092
                },
                {
                    "x": 0,
                    "y": 825.9780593325092
                }
            ]
        },
        {
            "id": "B3FSI-Pc9",
            "type": "RECTANGLE",
            "tags": [
                "letters"
            ],
            "boundingBox": {
                "height": 184.22744128553768,
                "width": 571.0632383599722,
                "left": 903.2939541348157,
                "top": 65.03862793572311
            },
            "points": [
                {
                    "x": 903.2939541348157,
                    "y": 65.03862793572311
                },
                {
                    "x": 1474.357192494788,
                    "y": 65.03862793572311
                },
                {
                    "x": 1474.357192494788,
                    "y": 249.2660692212608
                },
                {
                    "x": 903.2939541348157,
                    "y": 249.2660692212608
                }
            ]
        },
        {
            "id": "DkiBSI6oq",
            "type": "RECTANGLE",
            "tags": [
                "letters"
            ],
            "boundingBox": {
                "height": 88.10877626699629,
                "width": 285.5316191799861,
                "left": 412.2863099374565,
                "top": 595.0262669962917
            },
            "points": [
                {
                    "x": 412.2863099374565,
                    "y": 595.0262669962917
                },
                {
                    "x": 697.8179291174426,
                    "y": 595.0262669962917
                },
                {
                    "x": 697.8179291174426,
                    "y": 683.1350432632879
                },
                {
                    "x": 412.2863099374565,
                    "y": 683.1350432632879
                }
            ]
        },
        {
            "id": "W9Z-E8tNo",
            "type": "RECTANGLE",
            "tags": [
                "letters"
            ],
            "boundingBox": {
                "height": 98.78862793572311,
                "width": 430.9659485753996,
                "left": 1282.223766504517,
                "top": 420.14369592088997
            },
            "points": [
                {
                    "x": 1282.223766504517,
                    "y": 420.14369592088997
                },
                {
                    "x": 1713.1897150799164,
                    "y": 420.14369592088997
                },
                {
                    "x": 1713.1897150799164,
                    "y": 518.932323856613
                },
                {
                    "x": 1282.223766504517,
                    "y": 518.932323856613
                }
            ]
        },
        {
            "id": "A2Wmhqd-B",
            "type": "RECTANGLE",
            "tags": [
                "letters"
            ],
            "boundingBox": {
                "height": 49.39431396786156,
                "width": 180.12508686587907,
                "left": 640.4447533009034,
                "top": 697.8198393077873
            },
            "points": [
                {
                    "x": 640.4447533009034,
                    "y": 697.8198393077873
                },
                {
                    "x": 820.5698401667825,
                    "y": 697.8198393077873
                },
                {
                    "x": 820.5698401667825,
                    "y": 747.2141532756489
                },
                {
                    "x": 640.4447533009034,
                    "y": 747.2141532756489
                }
            ]
        }
    ],
    "version": "2.2.0"
}