{
    "asset": {
        "format": "png",
        "id": "ba3b0a6bb368bdf26c8c9e04eb2962b0",
        "name": "ffxiv_20221111_074608_332.png",
        "path": "file:D:/workspace/github/gelehrte-languageecho/image-FF14-letters/input/ffxiv_20221111_074608_332.png",
        "size": {
            "width": 1920,
            "height": 1080
        },
        "state": 2,
        "type": 1
    },
    "regions": [
        {
            "id": "o1Kbt-Vta",
            "type": "RECTANGLE",
            "tags": [
                "letters"
            ],
            "boundingBox": {
                "height": 84.9746192893401,
                "width": 401.5417558886509,
                "left": 757.8586723768736,
                "top": 43.900697969543145
            },
            "points": [
                {
                    "x": 757.8586723768736,
                    "y": 43.900697969543145
                },
                {
                    "x": 1159.4004282655246,
                    "y": 43.900697969543145
                },
                {
                    "x": 1159.4004282655246,
                    "y": 128.87531725888323
                },
                {
                    "x": 757.8586723768736,
                    "y": 128.87531725888323
                }
            ]
        },
        {
            "id": "yLS4K2E-h",
            "type": "RECTANGLE",
            "tags": [
                "letters"
            ],
            "boundingBox": {
                "height": 35.63451776649746,
                "width": 124.71092077087793,
                "left": 1164.8822269807279,
                "top": 101.46414974619289
            },
            "points": [
                {
                    "x": 1164.8822269807279,
                    "y": 101.46414974619289
                },
                {
                    "x": 1289.593147751606,
                    "y": 101.46414974619289
                },
                {
                    "x": 1289.593147751606,
                    "y": 137.09866751269035
                },
                {
                    "x": 1164.8822269807279,
                    "y": 137.09866751269035
                }
            ]
        },
        {
            "id": "ArIg-qirT",
            "type": "RECTANGLE",
            "tags": [
                "letters"
            ],
            "boundingBox": {
                "height": 112.38578680203045,
                "width": 291.9057815845824,
                "left": 677.0021413276231,
                "top": 202.8854695431472
            },
            "points": [
                {
                    "x": 677.0021413276231,
                    "y": 202.8854695431472
                },
                {
                    "x": 968.9079229122055,
                    "y": 202.8854695431472
                },
                {
                    "x": 968.9079229122055,
                    "y": 315.2712563451776
                },
                {
                    "x": 677.0021413276231,
                    "y": 315.2712563451776
                }
            ]
        },
        {
            "id": "_sGgLXr-9",
            "type": "RECTANGLE",
            "tags": [
                "letters"
            ],
            "boundingBox": {
                "height": 35.63451776649746,
                "width": 128.8222698072805,
                "left": 655.0749464668094,
                "top": 463.29156091370555
            },
            "points": [
                {
                    "x": 655.0749464668094,
                    "y": 463.29156091370555
                },
                {
                    "x": 783.8972162740898,
                    "y": 463.29156091370555
                },
                {
                    "x": 783.8972162740898,
                    "y": 498.92607868020303
                },
                {
                    "x": 655.0749464668094,
                    "y": 498.92607868020303
                }
            ]
        },
        {
            "id": "BRj0J5Wlx",
            "type": "RECTANGLE",
            "tags": [
                "letters"
            ],
            "boundingBox": {
                "height": 67.15736040609137,
                "width": 172.67665952890792,
                "left": 872.9764453961456,
                "top": 437.2509517766497
            },
            "points": [
                {
                    "x": 872.9764453961456,
                    "y": 437.2509517766497
                },
                {
                    "x": 1045.6531049250534,
                    "y": 437.2509517766497
                },
                {
                    "x": 1045.6531049250534,
                    "y": 504.4083121827411
                },
                {
                    "x": 872.9764453961456,
                    "y": 504.4083121827411
                }
            ]
        },
        {
            "id": "fSCxsQBTS",
            "type": "RECTANGLE",
            "tags": [
                "letters"
            ],
            "boundingBox": {
                "height": 52.08121827411167,
                "width": 41.113490364025694,
                "left": 1170.3640256959313,
                "top": 449.5859771573604
            },
            "points": [
                {
                    "x": 1170.3640256959313,
                    "y": 449.5859771573604
                },
                {
                    "x": 1211.477516059957,
                    "y": 449.5859771573604
                },
                {
                    "x": 1211.477516059957,
                    "y": 501.66719543147207
                },
                {
                    "x": 1170.3640256959313,
                    "y": 501.66719543147207
                }
            ]
        },
        {
            "id": "7xhMK38gQ",
            "type": "RECTANGLE",
            "tags": [
                "letters"
            ],
            "boundingBox": {
                "height": 21.928934010152282,
                "width": 565.9957173447538,
                "left": 671.5203426124197,
                "top": 512.6316624365481
            },
            "points": [
                {
                    "x": 671.5203426124197,
                    "y": 512.6316624365481
                },
                {
                    "x": 1237.5160599571734,
                    "y": 512.6316624365481
                },
                {
                    "x": 1237.5160599571734,
                    "y": 534.5605964467005
                },
                {
                    "x": 671.5203426124197,
                    "y": 534.5605964467005
                }
            ]
        },
        {
            "id": "FiGTZBSb1",
            "type": "RECTANGLE",
            "tags": [
                "letters"
            ],
            "boundingBox": {
                "height": 21.928934010152282,
                "width": 327.5374732334047,
                "left": 789.3790149892933,
                "top": 534.5605964467005
            },
            "points": [
                {
                    "x": 789.3790149892933,
                    "y": 534.5605964467005
                },
                {
                    "x": 1116.916488222698,
                    "y": 534.5605964467005
                },
                {
                    "x": 1116.916488222698,
                    "y": 556.4895304568528
                },
                {
                    "x": 789.3790149892933,
                    "y": 556.4895304568528
                }
            ]
        },
        {
            "id": "9A11xnVPi",
            "type": "RECTANGLE",
            "tags": [
                "letters"
            ],
            "boundingBox": {
                "height": 21.928934010152282,
                "width": 280.94218415417555,
                "left": 814.0471092077087,
                "top": 552.3778553299492
            },
            "points": [
                {
                    "x": 814.0471092077087,
                    "y": 552.3778553299492
                },
                {
                    "x": 1094.9892933618844,
                    "y": 552.3778553299492
                },
                {
                    "x": 1094.9892933618844,
                    "y": 574.3067893401014
                },
                {
                    "x": 814.0471092077087,
                    "y": 574.3067893401014
                }
            ]
        },
        {
            "id": "VDNlguq9P",
            "type": "RECTANGLE",
            "tags": [
                "letters"
            ],
            "boundingBox": {
                "height": 28.78172588832487,
                "width": 630.406852248394,
                "left": 640,
                "top": 568.8245558375634
            },
            "points": [
                {
                    "x": 640,
                    "y": 568.8245558375634
                },
                {
                    "x": 1270.406852248394,
                    "y": 568.8245558375634
                },
                {
                    "x": 1270.406852248394,
                    "y": 597.6062817258883
                },
                {
                    "x": 640,
                    "y": 597.6062817258883
                }
            ]
        },
        {
            "id": "xhPAUZMby",
            "type": "RECTANGLE",
            "tags": [
                "letters"
            ],
            "boundingBox": {
                "height": 13.705583756345177,
                "width": 82.22698072805139,
                "left": 664.6680942184154,
                "top": 627.7585659898476
            },
            "points": [
                {
                    "x": 664.6680942184154,
                    "y": 627.7585659898476
                },
                {
                    "x": 746.8950749464667,
                    "y": 627.7585659898476
                },
                {
                    "x": 746.8950749464667,
                    "y": 641.4641497461928
                },
                {
                    "x": 664.6680942184154,
                    "y": 641.4641497461928
                }
            ]
        },
        {
            "id": "JAoXFHyeE",
            "type": "RECTANGLE",
            "tags": [
                "letters"
            ],
            "boundingBox": {
                "height": 13.705583756345177,
                "width": 75.37473233404711,
                "left": 667.4089935760171,
                "top": 637.3524746192893
            },
            "points": [
                {
                    "x": 667.4089935760171,
                    "y": 637.3524746192893
                },
                {
                    "x": 742.7837259100642,
                    "y": 637.3524746192893
                },
                {
                    "x": 742.7837259100642,
                    "y": 651.0580583756345
                },
                {
                    "x": 667.4089935760171,
                    "y": 651.0580583756345
                }
            ]
        },
        {
            "id": "k8VsujcwR",
            "type": "RECTANGLE",
            "tags": [
                "letters"
            ],
            "boundingBox": {
                "height": 8.811188811188812,
                "width": 71.71690694626474,
                "left": 669.3577981651376,
                "top": 652.263986013986
            },
            "points": [
                {
                    "x": 669.3577981651376,
                    "y": 652.263986013986
                },
                {
                    "x": 741.0747051114024,
                    "y": 652.263986013986
                },
                {
                    "x": 741.0747051114024,
                    "y": 661.0751748251748
                },
                {
                    "x": 669.3577981651376,
                    "y": 661.0751748251748
                }
            ]
        },
        {
            "id": "trSke6_CH",
            "type": "RECTANGLE",
            "tags": [
                "letters"
            ],
            "boundingBox": {
                "height": 8.811188811188812,
                "width": 78.00786369593709,
                "left": 665.5832241153342,
                "top": 662.333916083916
            },
            "points": [
                {
                    "x": 665.5832241153342,
                    "y": 662.333916083916
                },
                {
                    "x": 743.5910878112713,
                    "y": 662.333916083916
                },
                {
                    "x": 743.5910878112713,
                    "y": 671.1451048951049
                },
                {
                    "x": 665.5832241153342,
                    "y": 671.1451048951049
                }
            ]
        },
        {
            "id": "6HHG0C-dB",
            "type": "RECTANGLE",
            "tags": [
                "letters"
            ],
            "boundingBox": {
                "height": 12.587412587412587,
                "width": 79.26605504587157,
                "left": 664.3250327653998,
                "top": 672.4038461538462
            },
            "points": [
                {
                    "x": 664.3250327653998,
                    "y": 672.4038461538462
                },
                {
                    "x": 743.5910878112713,
                    "y": 672.4038461538462
                },
                {
                    "x": 743.5910878112713,
                    "y": 684.9912587412588
                },
                {
                    "x": 664.3250327653998,
                    "y": 684.9912587412588
                }
            ]
        },
        {
            "id": "x6lpGhij-",
            "type": "RECTANGLE",
            "tags": [
                "letters"
            ],
            "boundingBox": {
                "height": 13.846153846153847,
                "width": 69.2005242463958,
                "left": 668.0996068152032,
                "top": 682.4737762237762
            },
            "points": [
                {
                    "x": 668.0996068152032,
                    "y": 682.4737762237762
                },
                {
                    "x": 737.300131061599,
                    "y": 682.4737762237762
                },
                {
                    "x": 737.300131061599,
                    "y": 696.31993006993
                },
                {
                    "x": 668.0996068152032,
                    "y": 696.31993006993
                }
            ]
        },
        {
            "id": "h0bNyMd8U",
            "type": "RECTANGLE",
            "tags": [
                "letters"
            ],
            "boundingBox": {
                "height": 11.328671328671328,
                "width": 65.4259501965924,
                "left": 671.8741808650066,
                "top": 695.0611888111888
            },
            "points": [
                {
                    "x": 671.8741808650066,
                    "y": 695.0611888111888
                },
                {
                    "x": 737.300131061599,
                    "y": 695.0611888111888
                },
                {
                    "x": 737.300131061599,
                    "y": 706.3898601398602
                },
                {
                    "x": 671.8741808650066,
                    "y": 706.3898601398602
                }
            ]
        },
        {
            "id": "F3gn1EVyl",
            "type": "RECTANGLE",
            "tags": [
                "letters"
            ],
            "boundingBox": {
                "height": 42.7972027972028,
                "width": 80.52424639580603,
                "left": 757.4311926605504,
                "top": 622.0541958041958
            },
            "points": [
                {
                    "x": 757.4311926605504,
                    "y": 622.0541958041958
                },
                {
                    "x": 837.9554390563566,
                    "y": 622.0541958041958
                },
                {
                    "x": 837.9554390563566,
                    "y": 664.8513986013986
                },
                {
                    "x": 757.4311926605504,
                    "y": 664.8513986013986
                }
            ]
        },
        {
            "id": "kZpLl_RDj",
            "type": "RECTANGLE",
            "tags": [
                "letter_180"
            ],
            "boundingBox": {
                "height": 41.53846153846154,
                "width": 76.74967234600263,
                "left": 756.173001310616,
                "top": 664.8513986013986
            },
            "points": [
                {
                    "x": 756.173001310616,
                    "y": 664.8513986013986
                },
                {
                    "x": 832.9226736566186,
                    "y": 664.8513986013986
                },
                {
                    "x": 832.9226736566186,
                    "y": 706.3898601398602
                },
                {
                    "x": 756.173001310616,
                    "y": 706.3898601398602
                }
            ]
        },
        {
            "id": "l61e51ps6",
            "type": "RECTANGLE",
            "tags": [
                "letters"
            ],
            "boundingBox": {
                "height": 17.622377622377623,
                "width": 189.98689384010484,
                "left": 840.4718217562255,
                "top": 625.8304195804196
            },
            "points": [
                {
                    "x": 840.4718217562255,
                    "y": 625.8304195804196
                },
                {
                    "x": 1030.4587155963302,
                    "y": 625.8304195804196
                },
                {
                    "x": 1030.4587155963302,
                    "y": 643.4527972027972
                },
                {
                    "x": 840.4718217562255,
                    "y": 643.4527972027972
                }
            ]
        },
        {
            "id": "gdt_r327p",
            "type": "RECTANGLE",
            "tags": [
                "letters"
            ],
            "boundingBox": {
                "height": 22.42132867132867,
                "width": 216.40891218872858,
                "left": 840.4718217562256,
                "top": 643.4527972027972
            },
            "points": [
                {
                    "x": 840.4718217562256,
                    "y": 643.4527972027972
                },
                {
                    "x": 1056.8807339449543,
                    "y": 643.4527972027972
                },
                {
                    "x": 1056.8807339449543,
                    "y": 665.8741258741259
                },
                {
                    "x": 840.4718217562256,
                    "y": 665.8741258741259
                }
            ]
        },
        {
            "id": "wbi47SO-6",
            "type": "RECTANGLE",
            "tags": [
                "letters"
            ],
            "boundingBox": {
                "height": 18.88111888111888,
                "width": 183.69593709043252,
                "left": 839.213630406291,
                "top": 666.1101398601398
            },
            "points": [
                {
                    "x": 839.213630406291,
                    "y": 666.1101398601398
                },
                {
                    "x": 1022.9095674967235,
                    "y": 666.1101398601398
                },
                {
                    "x": 1022.9095674967235,
                    "y": 684.9912587412588
                },
                {
                    "x": 839.213630406291,
                    "y": 684.9912587412588
                }
            ]
        },
        {
            "id": "YsonFyeN4",
            "type": "RECTANGLE",
            "tags": [
                "letters"
            ],
            "boundingBox": {
                "height": 26.433566433566433,
                "width": 186.21231979030145,
                "left": 837.9554390563566,
                "top": 682.4737762237762
            },
            "points": [
                {
                    "x": 837.9554390563566,
                    "y": 682.4737762237762
                },
                {
                    "x": 1024.167758846658,
                    "y": 682.4737762237762
                },
                {
                    "x": 1024.167758846658,
                    "y": 708.9073426573426
                },
                {
                    "x": 837.9554390563566,
                    "y": 708.9073426573426
                }
            ]
        },
        {
            "id": "2D_2jt3dT",
            "type": "RECTANGLE",
            "tags": [
                "letters"
            ],
            "boundingBox": {
                "height": 47.83216783216783,
                "width": 223.95806028833553,
                "left": 820.340760157274,
                "top": 721.4947552447552
            },
            "points": [
                {
                    "x": 820.340760157274,
                    "y": 721.4947552447552
                },
                {
                    "x": 1044.2988204456094,
                    "y": 721.4947552447552
                },
                {
                    "x": 1044.2988204456094,
                    "y": 769.3269230769231
                },
                {
                    "x": 820.340760157274,
                    "y": 769.3269230769231
                }
            ]
        }
    ],
    "version": "2.2.0"
}